gcody/__init__.py
gcody/gcode.py
gcody/gline.py
gcody/gsettings.py
gcody/helper.py
gcody/readg.py
gcody/visual.py
gcody-0.5.1.dist-info/METADATA
gcody-0.5.1.dist-info/RECORD
gcody-0.5.1.dist-info/WHEEL
gcody-0.5.1.dist-info/top_level.txt
