Metadata-Version: 2.1
Name: gcody
Version: 0.5.1
Summary: A package to read, write, and visualize GCODE
Home-page: https://github.com/rtZamb/gcody
Author: Ryan Zambrotta
Author-email: rtzamis2@gmail.com
License: MIT
Keywords: GCODE,3D Printing,visualiziation,CNC
Platform: UNKNOWN
Requires-Dist: numpy
Requires-Dist: matplotlib
